pcapfilter/__init__.py
pcapfilter/cli.py
pcapfilter/pcapfilter.py
pcapfilter/template.py
pcapfilter-0.2.1.dist-info/entry_points.txt
pcapfilter-0.2.1.dist-info/LICENSE
pcapfilter-0.2.1.dist-info/WHEEL
pcapfilter-0.2.1.dist-info/METADATA
pcapfilter-0.2.1.dist-info/RECORD
