Metadata-Version: 2.1
Name: pcapfilter
Version: 0.2.1
Summary: A tool to interact with netowkr traffic captured with tcpudmp or wireshark.
